json_operator/__init__.py
json_operator/equal.py
json_operator/intersection.py
json_operator/subtract.py
json_operator/union.py
json_operator/cli/__init__.py
json_operator/cli/main.py
json_operator-0.0.6.dist-info/LICENSE
json_operator-0.0.6.dist-info/METADATA
json_operator-0.0.6.dist-info/WHEEL
json_operator-0.0.6.dist-info/entry_points.txt
json_operator-0.0.6.dist-info/top_level.txt
json_operator-0.0.6.dist-info/RECORD
