Metadata-Version: 2.1
Name: json-operator
Version: 0.0.6
Summary: A library to operate on JSON objects
Home-page: https://github.com/forkend/json-operator-py
Author: Timothy Chu
Author-email: chujun.laiyang@gmail.com
Project-URL: Bug Tracker, https://github.com/forkend/json-operator-py/issues
Classifier: Programming Language :: Python :: 3
Classifier: License :: OSI Approved :: MIT License
Classifier: Operating System :: OS Independent
Requires-Python: >=3.6
License-File: LICENSE
